Metadata-Version: 2.1
Name: pyjudi-tjpr
Version: 1.0.3
Summary: Helper para efetuar login no sistema do projudi tjpr
Home-page: 
Author: Viiict0r
Author-email: victorh.cepil@hotmail.com
License: MIT License
Keywords: Projudi tjpr,Projudi paraná,Projudi crawler
License-File: LICENSE
